scanreader/__init__.py
scanreader/__main__.py
scanreader/lbm_widget.py
scanreader/multiroi.py
scanreader/scans.py
scanreader/utils.py
scanreader-0.6.0.dist-info/LICENSE
scanreader-0.6.0.dist-info/METADATA
scanreader-0.6.0.dist-info/WHEEL
scanreader-0.6.0.dist-info/top_level.txt
scanreader-0.6.0.dist-info/RECORD
