Metadata-Version: 2.1
Name: scanreader
Version: 0.6.0
Summary: Tiff reader for ScanImage BigTiff files.
Home-page: https://github.com/MillerBrainObservtory/scanreader
Author: Flynn OConnell
Author-email: foconnell@rockefeller.edu
License: MIT
Project-URL: homepage, https://millerbrainobservatory.github.io/
Project-URL: documentation, https://millerbrainobservatory.github.io/scanreader/index.html
Project-URL: source, https://github.com/MillerBrainObservatory/scanreader/
Keywords: ScanImage scanreader multiROI 2019 tiff
Classifier: Intended Audience :: Science/Research
Classifier: Intended Audience :: Developers
Classifier: Programming Language :: Python
Classifier: Programming Language :: Python :: 3
Classifier: Programming Language :: Python :: 3.10
Classifier: Programming Language :: Python :: 3.11
Classifier: Programming Language :: Python :: 3.12
Classifier: Programming Language :: Python :: 3 :: Only
Classifier: Topic :: Software Development
Classifier: Topic :: Scientific/Engineering
Classifier: Operating System :: Microsoft :: Windows
Classifier: Operating System :: POSIX
Classifier: Operating System :: Unix
Classifier: Operating System :: MacOS
Requires-Python: >=3.9
License-File: LICENSE
Requires-Dist: tifffile
Requires-Dist: numpy>=1.24.3
Requires-Dist: scipy>=1.9.0
Requires-Dist: dask
Requires-Dist: zarr
Requires-Dist: icecream
Provides-Extra: all
Requires-Dist: jupyterlab; extra == "all"
Requires-Dist: zarr; extra == "all"
Provides-Extra: notebook
Requires-Dist: jupyterlab; extra == "notebook"
